MimicD.py
MimicD-0.0.1.dist-info/LICENSE.txt.txt
MimicD-0.0.1.dist-info/METADATA
MimicD-0.0.1.dist-info/WHEEL
MimicD-0.0.1.dist-info/top_level.txt
MimicD-0.0.1.dist-info/RECORD
