Metadata-Version: 2.1
Name: MimicD
Version: 0.0.1
Summary: This package is for making Diagnostic pivot table
Author: Ariana Rahman
License: UNKNOWN
Keywords: Diagnostic Table,MIMIC-IV
Platform: UNKNOWN
Classifier: Programming Language :: Python :: 3
Classifier: License :: OSI Approved :: MIT License
Classifier: Operating System :: OS Independent
Requires-Python: >=3.6
License-File: LICENSE.txt.txt
Requires-Dist: pandas
Requires-Dist: numpy
Requires-Dist: datetime
